issn/__init__.py
issn/issn_api.py
issn-0.0.3.dist-info/METADATA
issn-0.0.3.dist-info/WHEEL
issn-0.0.3.dist-info/licenses/LICENSE
issn-0.0.3.dist-info/RECORD
