Metadata-Version: 2.1
Name: issn
Version: 0.0.3
Summary: This package parses ISSN and returns data by it.
Project-URL: Documentation, https://portal.issn.org/faq7
Author-email: Example Viktor <viktoral9599@gmail.com>
License-File: LICENSE
Classifier: License :: OSI Approved :: MIT License
Classifier: Operating System :: OS Independent
Classifier: Programming Language :: Python :: 3
Requires-Python: >=3.7
